<configuration changed-seconds="1513288720" changed-localtime="2017-12-14 21:58:40 UTC">
    <version>17.3R1-S2.1</version>
    <groups>
        <name>POC_Lab</name>
        <system>
            <host-name>QFX5110-171</host-name>
            <backup-router>
                <address>172.25.90.1</address>
            </backup-router>
            <authentication-order>radius</authentication-order>
            <authentication-order>password</authentication-order>
            <root-authentication>
                <encrypted-password>$1$1Y8rtyDJ$RMuoSrcwXfFasMJi3OnwI0</encrypted-password>
            </root-authentication>
            <name-server>
                <name>172.29.131.60</name>
            </name-server>
            <login>
                <message>\n \n System is in use for a customer POC testing \n \n *** Please do not make changes before contacting the Herndon POC admins *** \n\n</message>
                <user>
                    <name>lab</name>
                    <uid>2000</uid>
                    <class>super-user</class>
                    <authentication>
                        <encrypted-password>$1$60SRxtJo$LwXCbC3hOy.yKsSyedwkl/</encrypted-password>
                    </authentication>
                </user>
            </login>
            <services>
                <ftp>
                </ftp>
                <ssh>
                    <protocol-version>v2</protocol-version>
                </ssh>
                <telnet>
                </telnet>
                <xnm-clear-text>
                </xnm-clear-text>
                <netconf>
                    <ssh>
                    </ssh>
                </netconf>
            </services>
            <syslog>
                <host>
                    <name>172.25.45.6</name>
                    <contents>
                        <name>authorization</name>
                        <any/>
                    </contents>
                </host>
            </syslog>
            <ntp>
                <server>
                    <name>66.129.255.62</name>
                    <prefer/>
                </server>
            </ntp>
        </system>
        <interfaces>
            <interface>
                <name>em0</name>
                <unit>
                    <name>0</name>
                    <family>
                        <inet>
                            <address>
                                <name>172.25.90.171/24</name>
                            </address>
                        </inet>
                    </family>
                </unit>
            </interface>
        </interfaces>
        <snmp>
            <community>
                <name>public</name>
            </community>
        </snmp>
        <routing-options>
            <static>
                <route>
                    <name>0.0.0.0/0</name>
                    <next-hop>172.25.90.1</next-hop>
                </route>
            </static>
        </routing-options>
    </groups>
    <apply-groups>POC_Lab</apply-groups>
    <system>
        <root-authentication>
            <encrypted-password>$1$DBwh/7ma$FgJVx.7.uZW15cX9kM1EC/</encrypted-password>
        </root-authentication>
        <services>
            <extension-service>
                <request-response>
                    <grpc>
                        <undocumented><clear-text>
                            <port>50051</port>
                        </clear-text></undocumented>
                        <undocumented><skip-authentication/></undocumented>
                    </grpc>
                </request-response>
                <notification>
                    <allow-clients>
                        <address>0.0.0.0/0</address>
                    </allow-clients>
                </notification>
            </extension-service>
        </services>
    </system>
    <interfaces>
        <interface>
            <name>et-0/0/48</name>
            <mtu>9216</mtu>
            <unit>
                <name>0</name>
                <family>
                    <inet>
                        <address>
                            <name>10.0.1.8/31</name>
                        </address>
                    </inet>
                    <iso>
                    </iso>
                </family>
            </unit>
        </interface>
        <interface>
            <name>et-0/0/49</name>
            <mtu>9216</mtu>
            <unit>
                <name>0</name>
                <family>
                    <inet>
                        <address>
                            <name>10.0.1.10/31</name>
                        </address>
                    </inet>
                    <iso>
                    </iso>
                </family>
            </unit>
        </interface>
        <interface>
            <name>lo0</name>
            <unit>
                <name>0</name>
                <family>
                    <inet>
                        <address>
                            <name>191.168.100.5/32</name>
                        </address>
                    </inet>
                    <iso>
                        <address>
                            <name>49.0001.1911.6810.0005.00</name>
                        </address>
                    </iso>
                </family>
            </unit>
        </interface>
    </interfaces>
    <routing-options>
        <static>
            <route>
                <name>10.160.0.0/16</name>
                <next-hop>172.25.90.1</next-hop>
            </route>
        </static>
        <forwarding-table>
            <export>load-balance</export>
        </forwarding-table>
    </routing-options>
    <policy-options>
        <policy-statement>
            <name>load-balance</name>
            <then>
                <load-balance>
                    <per-packet/>
                </load-balance>
            </then>
        </policy-statement>
    </policy-options>
    <vlans>
        <vlan>
            <name>V2021</name>
            <vlan-id>2021</vlan-id>
        </vlan>
        <vlan>
            <name>V2022</name>
            <vlan-id>2022</vlan-id>
        </vlan>
        <vlan>
            <name>V2023</name>
            <vlan-id>2023</vlan-id>
        </vlan>
        <vlan>
            <name>V2024</name>
            <vlan-id>2024</vlan-id>
        </vlan>
        <vlan>
            <name>V2025</name>
            <vlan-id>2025</vlan-id>
        </vlan>
        <vlan>
            <name>V2031</name>
            <vlan-id>2031</vlan-id>
        </vlan>
    </vlans>
</configuration>